MANIFEST.in
README.rst
setup.py
web_crawler/__init__.py
web_crawler/crawler.py
web_crawler_poc.egg-info/PKG-INFO
web_crawler_poc.egg-info/SOURCES.txt
web_crawler_poc.egg-info/dependency_links.txt
web_crawler_poc.egg-info/not-zip-safe
web_crawler_poc.egg-info/requires.txt
web_crawler_poc.egg-info/top_level.txt