Metadata-Version: 1.0
Name: web-crawler-poc
Version: 0.1
Summary: Crawler to print web links
Home-page: http://github.com/storborg/funniest
Author: Aneesh Nair
Author-email: aneeshrnair@gmail.com
License: MIT
Platform: UNKNOWN
